npgamma/__init__.py
npgamma-0.8.2.dist-info/METADATA
npgamma-0.8.2.dist-info/RECORD
npgamma-0.8.2.dist-info/WHEEL
npgamma-0.8.2.dist-info/top_level.txt
