Metadata-Version: 2.1
Name: npgamma
Version: 0.8.2
Summary: `npgamma` is deprecated. Please use `gamma` module within the `pymedphys` package instead.
Home-page: https://github.com/SimonBiggs/npgamma/
Author: Simon Biggs
Author-email: me@simonbiggs.net
License: AGPL3+
Keywords: radiotherapy,gamma evaluation,gamma index,distance to agreement,medical physics
Platform: UNKNOWN
